cloudfs/__init__.py
cloudfs/base.py
cloudfs/version.py
cloudfs-0.1.0.dist-info/LICENSE
cloudfs-0.1.0.dist-info/METADATA
cloudfs-0.1.0.dist-info/WHEEL
cloudfs-0.1.0.dist-info/RECORD
